mtn_payments_v1/__init__.py
mtn_payments_v1/_base_client.py
mtn_payments_v1/_client.py
mtn_payments_v1/_compat.py
mtn_payments_v1/_constants.py
mtn_payments_v1/_exceptions.py
mtn_payments_v1/_files.py
mtn_payments_v1/_models.py
mtn_payments_v1/_qs.py
mtn_payments_v1/_resource.py
mtn_payments_v1/_response.py
mtn_payments_v1/_streaming.py
mtn_payments_v1/_types.py
mtn_payments_v1/_version.py
mtn_payments_v1/py.typed
mtn_payments_v1/_utils/__init__.py
mtn_payments_v1/_utils/_logs.py
mtn_payments_v1/_utils/_proxy.py
mtn_payments_v1/_utils/_reflection.py
mtn_payments_v1/_utils/_streams.py
mtn_payments_v1/_utils/_sync.py
mtn_payments_v1/_utils/_transform.py
mtn_payments_v1/_utils/_typing.py
mtn_payments_v1/_utils/_utils.py
mtn_payments_v1/lib/.keep
mtn_payments_v1/resources/__init__.py
mtn_payments_v1/resources/reverse_payments.py
mtn_payments_v1/resources/payments/__init__.py
mtn_payments_v1/resources/payments/history.py
mtn_payments_v1/resources/payments/payment_agreement.py
mtn_payments_v1/resources/payments/payments.py
mtn_payments_v1/types/__init__.py
mtn_payments_v1/types/inbound_response.py
mtn_payments_v1/types/order_response.py
mtn_payments_v1/types/payment_create_params.py
mtn_payments_v1/types/payment_fee_params.py
mtn_payments_v1/types/payment_payment_link_params.py
mtn_payments_v1/types/payment_response.py
mtn_payments_v1/types/payment_transaction_status_params.py
mtn_payments_v1/types/payment_transaction_status_response.py
mtn_payments_v1/types/reverse_payment_history_params.py
mtn_payments_v1/types/reverse_transaction_history.py
mtn_payments_v1/types/payments/__init__.py
mtn_payments_v1/types/payments/history_list_params.py
mtn_payments_v1/types/payments/payment_agreement_create_params.py
mtn_payments_v1/types/payments/payment_agreement_eligibility_params.py
mtn_payments_v1/types/payments/payment_history_response.py
mtn_payments_v1/types/payments/promise_to_pay_eligibility_response.py
mtn_payments_v1/types/payments/promise_to_pay_response.py
mtn_payments_v1-0.0.1a1.dist-info/METADATA
mtn_payments_v1-0.0.1a1.dist-info/WHEEL
mtn_payments_v1-0.0.1a1.dist-info/licenses/LICENSE
mtn_payments_v1-0.0.1a1.dist-info/RECORD
